<?xml version="1.0" encoding="UTF-8" standalone="yes"?>
<ns2:cdsListSpecificationFile xmlns:ns2="org.cdsframework.util.support.data.cds.list">
    <listId>fde739ed9a6d3d03ceec9ba7eb6f3bac</listId>
    <code>SupportedEvaluationStatusConcept</code>
    <name>Supported Evaluation Status Concepts</name>
    <listType>CODE_SYSTEM</listType>
    <codeSystem>2.16.840.1.113883.3.795.12.100.2</codeSystem>
    <codeSystemName>ICE Evaluation</codeSystemName>
    <cdsListItem>
        <cdsListItemKey>ACCEPTED</cdsListItemKey>
        <cdsListItemValue>Accepted Immunization</cdsListItemValue>
    </cdsListItem>
    <cdsListItem>
        <cdsListItemKey>IGNORE</cdsListItemKey>
        <cdsListItemValue>Ignore Immunization</cdsListItemValue>
    </cdsListItem>
    <cdsListItem>
        <cdsListItemKey>INVALID</cdsListItemKey>
        <cdsListItemValue>Invalid Immunization</cdsListItemValue>
    </cdsListItem>
    <cdsListItem>
        <cdsListItemKey>VALID</cdsListItemKey>
        <cdsListItemValue>Valid Immunization</cdsListItemValue>
    </cdsListItem>
</ns2:cdsListSpecificationFile>
